[
  {
    "Author": "John-P",
    "Name": "HuntTrack",
    "Punchline": "Liste de choses à tracker.",
    "Description": "Liste de choses à tracker.",
    "Tags": [
      "plugin"
    ],
    "InternalName": "HuntTrack",
    "AssemblyVersion": "1.0.5",
    "TestingAssemblyVersion": "1.0.5",
    "RepoUrl": "https://github.com/JohnP-lab/HuntTrack",
    "ApplicableVersion": "any",
    "DalamudApiLevel": 12,
    "TestingDalamudApiLevel": 12,
    "IsHide": "False",
    "IsTestingExclusive": "False",
    "DownloadCount": 1,
    "LastUpdate": 1618608322,
    "DownloadLinkInstall": "https://github.com/JohnP-lab/HuntTrack/releases/download/1.0.5/HuntTrack.zip",
    "DownloadLinkUpdate": "https://github.com/JohnP-lab/HuntTrack/releases/download/1.0.5/HuntTrack.zip",
    "DownloadLinkTesting": "https://github.com/JohnP-lab/HuntTrack/releases/download/1.0.5/HuntTrack.zip",
    "IconUrl": "https://raw.githubusercontent.com/JohnP-lab/HuntTrack/master/images/icon.png"
  }
]
